msg91/__init__.py
msg91/services/__init__.py
msg91/services/otp_service.py
tests/__init__.py
tests/test_otp_service.py
test_prashant-0.1.0.dist-info/METADATA
test_prashant-0.1.0.dist-info/WHEEL
test_prashant-0.1.0.dist-info/top_level.txt
test_prashant-0.1.0.dist-info/RECORD
